streamlitopencvplayer/__init__.py
streamlitopencvplayer/app.py
test/__init__.py
test/app.py
test/test.py
streamlitopencvplayer-1.6.4.dist-info/METADATA
streamlitopencvplayer-1.6.4.dist-info/WHEEL
streamlitopencvplayer-1.6.4.dist-info/top_level.txt
streamlitopencvplayer-1.6.4.dist-info/RECORD
