Metadata-Version: 2.1
Name: streamlitopencvplayer
Version: 1.6.4
Summary: Streamlit Opencv player
Author: Nafaa Bougraine
Author-email: bougraine.nafaa@gmail.com
Keywords: python,package
Classifier: Programming Language :: Python :: 3
Classifier: Operating System :: Microsoft :: Windows
